LICENSE
README.md
pyproject.toml
jira_utils/__init__.py
jira_utils.egg-info/PKG-INFO
jira_utils.egg-info/SOURCES.txt
jira_utils.egg-info/dependency_links.txt
jira_utils.egg-info/top_level.txt