Metadata-Version: 2.2
Name: jira-utils
Version: 0.0.1
Summary: Data Processor
Author-email: Ramin-RX7 <rawmin.rx@gmail.com>
License: MIT
Keywords: jira,utils,utility
Classifier: Programming Language :: Python :: 3
Requires-Python: >=3.6
License-File: LICENSE
